setup.py
ebulksms/__init__.py
ebulksms/ebulksms.py
ebulksms.egg-info/PKG-INFO
ebulksms.egg-info/SOURCES.txt
ebulksms.egg-info/dependency_links.txt
ebulksms.egg-info/requires.txt
ebulksms.egg-info/top_level.txt