Metadata-Version: 2.1
Name: ebulksms
Version: 1.0.0
Summary: The EBulkSMS Python library provides a simple interface for sending SMS messages
Home-page: https://github.com/emmyvera/ebulksms
Author: Oluwaloni Emmanuel
Author-email: emmyvera01@gmail.com
License: MIT
Keywords: SMS,Nigeria,BulkSMS,EBulkSMS,bulk sms
Classifier: Programming Language :: Python :: 3
Classifier: License :: OSI Approved :: MIT License
Classifier: Operating System :: OS Independent
Requires-Python: >=3.6
